sphinxcontrib_cacoo-2.0.0-py3.6-nspkg.pth
sphinxcontrib/cacoo.py
sphinxcontrib_cacoo-2.0.0.dist-info/METADATA
sphinxcontrib_cacoo-2.0.0.dist-info/RECORD
sphinxcontrib_cacoo-2.0.0.dist-info/WHEEL
sphinxcontrib_cacoo-2.0.0.dist-info/namespace_packages.txt
sphinxcontrib_cacoo-2.0.0.dist-info/top_level.txt
