Metadata-Version: 2.1
Name: sphinxcontrib-cacoo
Version: 2.0.0
Summary: Sphinx "cacoo" extension; embed diagram from cacoo
Home-page: https://github.com/tk0miya/sphinxcontrib-cacoo/
Author: Takeshi KOMIYA
Author-email: i.tkomiya@gmail.com
License: BSD
Platform: any
Classifier: Development Status :: 5 - Production/Stable
Classifier: Environment :: Console
Classifier: Environment :: Web Environment
Classifier: Framework :: Sphinx :: Extension
Classifier: Intended Audience :: Developers
Classifier: License :: OSI Approved :: BSD License
Classifier: Operating System :: OS Independent
Classifier: Programming Language :: Python
Classifier: Programming Language :: Python :: 2.7
Classifier: Programming Language :: Python :: 3.4
Classifier: Programming Language :: Python :: 3.5
Classifier: Programming Language :: Python :: 3.6
Classifier: Topic :: Documentation
Classifier: Topic :: Documentation :: Sphinx
Classifier: Topic :: Utilities
Requires-Dist: Sphinx (>=1.6)
